README
setup.py
metamx/__init__.py
metamx/config.yaml
metamx/provision-ec2.py
metamx.egg-info/PKG-INFO
metamx.egg-info/SOURCES.txt
metamx.egg-info/dependency_links.txt
metamx.egg-info/requires.txt
metamx.egg-info/top_level.txt