Metadata-Version: 1.0
Name: metamx
Version: 0.1.5
Summary: Metamx Operations API
Home-page: https://github.com/metamx/operations
Author: ops
Author-email: ops@metamarkets.com
License: UNKNOWN
Platform: UNKNOWN
